combined_bukmacherska1/__init__.py
combined_bukmacherska1/combined_library.py
combined_bukmacherska2/__init__.py
combined_bukmacherska2/combined_library.py
combined_bukmacherska3/__init__.py
combined_bukmacherska3/combined_library3.py
combined_bukmacherska-0.9.0.dist-info/LICENSE
combined_bukmacherska-0.9.0.dist-info/METADATA
combined_bukmacherska-0.9.0.dist-info/WHEEL
combined_bukmacherska-0.9.0.dist-info/top_level.txt
combined_bukmacherska-0.9.0.dist-info/RECORD
