Metadata-Version: 2.2
Name: combined_bukmacherska
Version: 0.9.0
Summary: Tools for analyzing sports statistics and using machine learning to assist in betting strategies.
Home-page: https://github.com/your-repo-url
Author: Twoje Imię
Author-email: your.email@example.com
Classifier: Programming Language :: Python :: 3
Classifier: License :: OSI Approved :: MIT License
Classifier: Operating System :: OS Independent
Requires-Python: >=3.6
License-File: LICENSE
Requires-Dist: numpy
Requires-Dist: scipy
Requires-Dist: matplotlib
Requires-Dist: scikit-learn
Requires-Dist: xgboost
Requires-Dist: catboost
Dynamic: author
Dynamic: author-email
Dynamic: classifier
Dynamic: description
Dynamic: description-content-type
Dynamic: home-page
Dynamic: requires-dist
Dynamic: requires-python
Dynamic: summary
